Soundboard/Decomposition.py
Soundboard/Soundboard.py
Soundboard/__init__.py
Soundboard-2.0.3.dist-info/LICENSE
Soundboard-2.0.3.dist-info/METADATA
Soundboard-2.0.3.dist-info/WHEEL
Soundboard-2.0.3.dist-info/top_level.txt
Soundboard-2.0.3.dist-info/RECORD
