Metadata-Version: 2.1
Name: Soundboard
Version: 2.0.3
Summary: This is a wave form generator and interpreter!
Home-page: https://github.com/ghostlypi/Soundboard.git
Author: ghostlypi
Author-email: contact@parthiyer.com
License: UNKNOWN
Project-URL: Bug Tracker, https://github.com/ghostlypi/Soundboard/issues
Platform: UNKNOWN
Classifier: Programming Language :: Python :: 3
Classifier: License :: OSI Approved :: MIT License
Classifier: Operating System :: OS Independent
Requires-Python: >=3.6
License-File: LICENSE
